cbuild/__main__.py
cbuild/cbuild.py
cbuild-0.1.117.dist-info/licenses/LICENSE
cbuild-0.1.117.dist-info/METADATA
cbuild-0.1.117.dist-info/WHEEL
cbuild-0.1.117.dist-info/entry_points.txt
cbuild-0.1.117.dist-info/top_level.txt
cbuild-0.1.117.dist-info/RECORD
