Metadata-Version: 2.4
Name: cbuild
Version: 0.1.117
Summary: A tool like Nuitka and PyInstaller for packaging Python applications
Requires-Python: >=3.7
License-File: LICENSE
Requires-Dist: toml
Dynamic: license-file
